odoo/addons/stock_picking_batch_validate_confirm/README.rst
odoo/addons/stock_picking_batch_validate_confirm/__init__.py
odoo/addons/stock_picking_batch_validate_confirm/__manifest__.py
odoo/addons/stock_picking_batch_validate_confirm/i18n/es.po
odoo/addons/stock_picking_batch_validate_confirm/i18n/it.po
odoo/addons/stock_picking_batch_validate_confirm/i18n/stock_picking_batch_validate_confirm.pot
odoo/addons/stock_picking_batch_validate_confirm/models/__init__.py
odoo/addons/stock_picking_batch_validate_confirm/models/stock_picking_batch.py
odoo/addons/stock_picking_batch_validate_confirm/readme/CONFIGURE.md
odoo/addons/stock_picking_batch_validate_confirm/readme/CONTRIBUTORS.md
odoo/addons/stock_picking_batch_validate_confirm/readme/DESCRIPTION.md
odoo/addons/stock_picking_batch_validate_confirm/readme/USAGE.md
odoo/addons/stock_picking_batch_validate_confirm/security/ir.model.access.csv
odoo/addons/stock_picking_batch_validate_confirm/security/stock_picking_batch_validate_confirm_groups.xml
odoo/addons/stock_picking_batch_validate_confirm/static/description/icon.png
odoo/addons/stock_picking_batch_validate_confirm/static/description/index.html
odoo/addons/stock_picking_batch_validate_confirm/tests/__init__.py
odoo/addons/stock_picking_batch_validate_confirm/tests/test_batch_confirm.py
odoo/addons/stock_picking_batch_validate_confirm/wizards/__init__.py
odoo/addons/stock_picking_batch_validate_confirm/wizards/stock_picking_batch_confirm.py
odoo/addons/stock_picking_batch_validate_confirm/wizards/stock_picking_batch_confirm.xml
odoo_addon_stock_picking_batch_validate_confirm-18.0.1.0.1.dist-info/METADATA
odoo_addon_stock_picking_batch_validate_confirm-18.0.1.0.1.dist-info/WHEEL
odoo_addon_stock_picking_batch_validate_confirm-18.0.1.0.1.dist-info/top_level.txt
odoo_addon_stock_picking_batch_validate_confirm-18.0.1.0.1.dist-info/RECORD
